aoutools/__init__.py
aoutools/_utils/__init__.py
aoutools/_utils/helpers.py
aoutools/data/prs_weights_header.csv
aoutools/data/prs_weights_noheader.tsv
aoutools/prs/__init__.py
aoutools/prs/_calculator.py
aoutools/prs/_calculator_batch.py
aoutools/prs/_calculator_utils.py
aoutools/prs/_config.py
aoutools/prs/_downloader.py
aoutools/prs/_downloader_deprecated.py
aoutools/prs/_reader.py
aoutools/prs/_utils.py
aoutools/prs/_workflow.py
aoutools-0.1.1.dist-info/licenses/LICENSE
aoutools-0.1.1.dist-info/METADATA
aoutools-0.1.1.dist-info/WHEEL
aoutools-0.1.1.dist-info/top_level.txt
aoutools-0.1.1.dist-info/RECORD
