Metadata-Version: 2.4
Name: aoutools
Version: 0.1.1
Summary: A library of tools for analyzing All of Us data.
Author-email: Jaehyun Joo <jaehyunjoo@outlook.com>
License: MIT License
Project-URL: Homepage, https://github.com/dokyoonkimlab/aoutools
Project-URL: Repository, https://github.com/dokyoonkimlab/aoutools
Project-URL: Issues, https://github.com/dokyoonkimlab/aoutools/issues
Project-URL: Documentation, https://aoutools.readthedocs.io
Keywords: all-of-us,genomics,bioinformatics,prs,hail
Classifier: Programming Language :: Python :: 3
Classifier: License :: OSI Approved :: MIT License
Classifier: Operating System :: OS Independent
Classifier: Intended Audience :: Science/Research
Classifier: Topic :: Scientific/Engineering :: Bio-Informatics
Requires-Python: >=3.8
License-File: LICENSE
Requires-Dist: hail
Requires-Dist: pandas
Requires-Dist: google-cloud-storage
Provides-Extra: test
Requires-Dist: pytest; extra == "test"
Requires-Dist: pytest-mock; extra == "test"
Dynamic: license-file
